apk_signature/__init__.py
apk_signature/version.py
apk_signature-1.0.0.dist-info/METADATA
apk_signature-1.0.0.dist-info/WHEEL
apk_signature-1.0.0.dist-info/entry_points.txt
apk_signature-1.0.0.dist-info/top_level.txt
apk_signature-1.0.0.dist-info/RECORD
