Metadata-Version: 2.1
Name: apk-signature
Version: 1.0.0
Summary: install IPA package to iOS device with command line
Home-page: https://github.com/floatinghotpot/apk-signature
Download-URL: https://github.com/floatinghotpot/apk-signature
Author: Liming Xie
Author-email: liming.xie@gmail.com
License: GPLv3+
Keywords: ios,installer
Platform: any
Classifier: Development Status :: 4 - Beta
Classifier: Intended Audience :: Developers
Classifier: License :: OSI Approved :: GNU General Public License v3 or later (GPLv3+)
Classifier: Programming Language :: Python :: 3
Classifier: Programming Language :: Python :: 3.7
Classifier: Operating System :: OS Independent
Requires-Python: >=3.7
